[
    {
        "religion": [
            "Faith of the Seven"
        ],
        "rulers": [
            "House Smallwood"
        ],
        "founder": [],
        "_id": "5c9817ab4d1c4e54abc7edbb",
        "name": "Acorn Hall",
        "location": "Westeros",
        "type": "Castle",
        "__v": 0
    },
    {
        "religion": [
            "Faith of the Seven"
        ],
        "rulers": [
            "House Buckwell"
        ],
        "founder": [],
        "_id": "5c9817ab4d1c4e54abc7edbc",
        "name": "Antlers",
        "location": "The Crownlands",
        "type": "Castle",
        "__v": 0
    },
    {
        "religion": [
            "Faith of the Seven"
        ],
        "rulers": [
            "House Marbrand"
        ],
        "founder": [],
        "_id": "5c9817ab4d1c4e54abc7edbd",
        "name": "Ashemark",
        "location": "The Westerlands",
        "type": "Stronghold",
        "__v": 0
    },
    {
        "religion": [
            "Faith of the Seven"
        ],
        "rulers": [
            "House Ashford"
        ],
        "founder": [],
        "_id": "5c9817ab4d1c4e54abc7edbe",
        "name": "Ashford",
        "location": "The Reach",
        "type": "Castle and town",
        "__v": 0
    },
    {
        "religion": [
            "Faith of the Seven"
        ],
        "rulers": [],
        "founder": [],
        "_id": "5c9817ab4d1c4e54abc7edbf",
        "name": "Bandallon",
        "location": "Westeros",
        "type": "Castle",
        "__v": 0
    },
    {
        "religion": [
            "Faith of the Seven"
        ],
        "rulers": [],
        "founder": [],
        "_id": "5c9817ab4d1c4e54abc7edc0",
        "name": "The Banefort",
        "location": "The Westerlands",
        "type": "Castle",
        "__v": 0
    },
    {
        "religion": [
            "Faith of the Seven"
        ],
        "rulers": [],
        "founder": [],
        "_id": "5c9817ab4d1c4e54abc7edc1",
        "name": "Bitterbridge",
        "location": "Westeros",
        "type": "Castle",
        "__v": 0
    },
    {
        "religion": [
            "Faith of the Seven"
        ],
        "rulers": [
            "House Bulwer"
        ],
        "founder": [],
        "_id": "5c9817ab4d1c4e54abc7edc2",
        "name": "Blackcrown",
        "location": "Westeros",
        "type": "Castle",
        "__v": 0
    },
    {
        "religion": [
            "Faith of the Seven"
        ],
        "rulers": [
            "House Dondarrion"
        ],
        "founder": [],
        "_id": "5c9817ab4d1c4e54abc7edc3",
        "name": "Blackhaven",
        "location": "The Stormlands",
        "type": "Castle",
        "__v": 0
    },
    {
        "religion": [
            "Faith of the Seven"
        ],
        "rulers": [
            "House Blackmont"
        ],
        "founder": [],
        "_id": "5c9817ab4d1c4e54abc7edc4",
        "name": "Blackmont",
        "location": "Dorne",
        "type": "Castle",
        "__v": 0
    },
    {
        "religion": [
            "Faith of the Seven"
        ],
        "rulers": [
            "Knight of the Gate",
            "House Arryn"
        ],
        "founder": [],
        "_id": "5c9817ab4d1c4e54abc7edc5",
        "name": "Bloody Gate",
        "location": "The Vale",
        "type": "Castle",
        "__v": 0
    },
    {
        "religion": [
            "Faith of the Seven"
        ],
        "rulers": [
            "House Florent"
        ],
        "founder": [],
        "_id": "5c9817ab4d1c4e54abc7edc6",
        "name": "Brightwater Keep",
        "location": "the Reach",
        "type": "Castle",
        "__v": 0
    },
    {
        "religion": [
            "Faith of the Seven"
        ],
        "rulers": [],
        "founder": [],
        "_id": "5c9817ab4d1c4e54abc7edc7",
        "name": "Bronzegate",
        "location": "The Stormlands",
        "type": "Castle",
        "__v": 0
    },
    {
        "religion": [
            "Faith of the Seven"
        ],
        "rulers": [
            "House Reyne"
        ],
        "founder": [],
        "_id": "5c9817ab4d1c4e54abc7edc8",
        "name": "Castamere",
        "location": "The Westerlands",
        "type": "Castle",
        "__v": 0
    },
    {
        "religion": [
            "Faith of the Seven"
        ],
        "rulers": [
            "House Lannister",
            "House Targaryen",
            "House Casterly"
        ],
        "founder": [
            "Corlos"
        ],
        "_id": "5c9817ab4d1c4e54abc7edc9",
        "name": "Casterly Rock",
        "location": "The Westerlands",
        "type": "Castle, built into a natural rock formation, regional capital",
        "age": 6000,
        "__v": 0
    },
    {
        "religion": [
            "Old Gods of the Forest",
            "Faith of the Seven"
        ],
        "rulers": [
            "Night&apos;s Watch"
        ],
        "founder": [
            "Brandon Stark (the Builder)"
        ],
        "_id": "5c9817ab4d1c4e54abc7edca",
        "name": "Castle Black",
        "location": "The Wall",
        "type": "Castle",
        "__v": 0
    },
    {
        "religion": [
            "Old Gods of the Forest"
        ],
        "rulers": [
            "House Cerwyn"
        ],
        "founder": [],
        "_id": "5c9817ab4d1c4e54abc7edcb",
        "name": "Castle Cerwyn",
        "location": "Westeros",
        "type": "Castle",
        "__v": 0
    },
    {
        "religion": [
            "Faith of the Seven"
        ],
        "rulers": [
            "House Stokeworth"
        ],
        "founder": [],
        "_id": "5c9817ab4d1c4e54abc7edcc",
        "name": "Castle Stokeworth",
        "location": "The Crownlands",
        "type": "Castle",
        "__v": 0
    },
    {
        "religion": [
            "Faith of the Seven"
        ],
        "rulers": [
            "House Fossoway"
        ],
        "founder": [],
        "_id": "5c9817ab4d1c4e54abc7edcd",
        "name": "Cider Hall",
        "location": "The Reach",
        "type": "Castle",
        "__v": 0
    },
    {
        "religion": [
            "Faith of the Seven"
        ],
        "rulers": [
            "House Hightower",
            "Conclave",
            "Maesters"
        ],
        "founder": [
            "Urrigon Hightower"
        ],
        "_id": "5c9817ab4d1c4e54abc7edce",
        "name": "The Citadel",
        "location": "Oldtown",
        "type": "LighthouseOrder headquarters and Training center",
        "__v": 0
    },
    {
        "religion": [
            "Faith of the Seven"
        ],
        "rulers": [
            "House Clegane"
        ],
        "founder": [
            "Clegane (founder)"
        ],
        "_id": "5c9817ab4d1c4e54abc7edcf",
        "name": "Clegane's Keep",
        "location": "The Westerlands",
        "type": "Castle",
        "__v": 0
    },
    {
        "religion": [],
        "rulers": [],
        "founder": [],
        "_id": "5c9817ab4d1c4e54abc7edd0",
        "name": "Coldwater",
        "location": "The Vale of Arryn",
        "type": "Castle",
        "__v": 0
    },
    {
        "religion": [
            "Faith of the Seven"
        ],
        "rulers": [
            "House Westerling"
        ],
        "founder": [],
        "_id": "5c9817ab4d1c4e54abc7edd1",
        "name": "The Crag",
        "location": "Westeros",
        "type": "Castle",
        "__v": 0
    },
    {
        "religion": [
            "Faith of the Seven"
        ],
        "rulers": [
            "House Crakehall"
        ],
        "founder": [],
        "_id": "5c9817ab4d1c4e54abc7edd2",
        "name": "Crakehall",
        "location": "The Westerlands",
        "type": "Castle",
        "__v": 0
    },
    {
        "religion": [
            "Faith of the Seven"
        ],
        "rulers": [
            "House Morrigen"
        ],
        "founder": [],
        "_id": "5c9817ab4d1c4e54abc7edd3",
        "name": "Crow's Nest",
        "location": "The Stormlands",
        "type": "Castle",
        "__v": 0
    },
    {
        "religion": [
            "Faith of the Seven"
        ],
        "rulers": [],
        "founder": [],
        "_id": "5c9817ab4d1c4e54abc7edd4",
        "name": "Deep Den",
        "location": "The Westerlands",
        "type": "Castle",
        "__v": 0
    },
    {
        "religion": [
            "Old Gods of the Forest",
            "Faith of the Seven"
        ],
        "rulers": [
            "Night&apos;s Watch"
        ],
        "founder": [],
        "_id": "5c9817ab4d1c4e54abc7edd5",
        "name": "Deep Lake",
        "location": "Westeros",
        "type": "Castle",
        "__v": 0
    },
    {
        "religion": [
            "Old Gods of the Forest",
            "Drowned God"
        ],
        "rulers": [
            "House Glover",
            "House Greyjoy"
        ],
        "founder": [],
        "_id": "5c9817ab4d1c4e54abc7edd6",
        "name": "Deepwood Motte",
        "location": "The North",
        "type": "Motte-and-bailey castle",
        "__v": 0
    },
    {
        "religion": [
            "R&apos;hllor",
            "Faith of the Seven"
        ],
        "rulers": [
            "House Targaryen",
            "House Baratheon of Dragonstone"
        ],
        "founder": [
            "Valyrian Freehold"
        ],
        "_id": "5c9817ab4d1c4e54abc7edd7",
        "name": "Dragonstone (castle)",
        "location": "Dragonstone",
        "type": "Castle",
        "age": 500,
        "__v": 0
    },
    {
        "religion": [
            "Old Gods of the Forest"
        ],
        "rulers": [
            "House Bolton"
        ],
        "founder": [],
        "_id": "5c9817ab4d1c4e54abc7edd8",
        "name": "The Dreadfort",
        "location": "The North",
        "type": "Castle, temporary regional capital",
        "__v": 0
    },
    {
        "religion": [],
        "rulers": [],
        "founder": [],
        "_id": "5c9817ab4d1c4e54abc7edd9",
        "name": "Dyre Den",
        "location": "Crackclaw Point",
        "type": "Castle",
        "__v": 0
    },
    {
        "religion": [
            "Old Gods of the Forest",
            "Faith of the Seven"
        ],
        "rulers": [
            "Night&apos;s Watch"
        ],
        "founder": [],
        "_id": "5c9817ab4d1c4e54abc7edda",
        "name": "Eastwatch-by-the-Sea",
        "location": "The Wall",
        "type": "CastlePort",
        "__v": 0
    },
    {
        "religion": [
            "Faith of the Seven"
        ],
        "rulers": [
            "House Tarth"
        ],
        "founder": [],
        "_id": "5c9817ab4d1c4e54abc7eddb",
        "name": "Evenfall Hall",
        "location": "Tarth",
        "type": "Castle",
        "__v": 0
    },
    {
        "religion": [
            "Faith of the Seven"
        ],
        "rulers": [
            "House Arryn"
        ],
        "founder": [
            "Mountain King"
        ],
        "_id": "5c9817ab4d1c4e54abc7eddc",
        "name": "The Eyrie",
        "location": "Mountains of the Moon",
        "type": "CastleRegional capital",
        "age": 6000,
        "__v": 0
    },
    {
        "religion": [
            "Faith of the Seven"
        ],
        "rulers": [],
        "founder": [],
        "_id": "5c9817ab4d1c4e54abc7eddd",
        "name": "Faircastle",
        "location": "Fair Isle",
        "type": "Castle",
        "__v": 0
    },
    {
        "religion": [
            "Faith of the Seven"
        ],
        "rulers": [],
        "founder": [],
        "_id": "5c9817ab4d1c4e54abc7edde",
        "name": "Feastfires",
        "location": "The Westerlands",
        "type": "Castle",
        "__v": 0
    },
    {
        "religion": [
            "Faith of the Seven"
        ],
        "rulers": [],
        "founder": [],
        "_id": "5c9817ab4d1c4e54abc7eddf",
        "name": "Felwood",
        "location": "The Stormlands",
        "type": "Castle",
        "__v": 0
    },
    {
        "religion": [
            "Old Gods of the Forest"
        ],
        "rulers": [],
        "founder": [],
        "_id": "5c9817ab4d1c4e54abc7ede0",
        "name": "Flint's Finger",
        "location": "The North",
        "type": "Castle",
        "__v": 0
    },
    {
        "religion": [
            "Faith of the Seven"
        ],
        "rulers": [],
        "founder": [],
        "_id": "5c9817ab4d1c4e54abc7ede1",
        "name": "Ghost Hill",
        "location": "Dorne",
        "type": "Castle",
        "__v": 0
    },
    {
        "religion": [
            "Faith of the Seven"
        ],
        "rulers": [
            "House Allyrion"
        ],
        "founder": [],
        "_id": "5c9817ab4d1c4e54abc7ede2",
        "name": "Godsgrace",
        "location": "Dorne",
        "type": "Castle",
        "__v": 0
    },
    {
        "religion": [
            "Faith of the Seven"
        ],
        "rulers": [
            "House Lefford"
        ],
        "founder": [],
        "_id": "5c9817ab4d1c4e54abc7ede3",
        "name": "Golden Tooth",
        "location": "The Westerlands",
        "type": "Stronghold",
        "__v": 0
    },
    {
        "religion": [
            "Faith of the Seven"
        ],
        "rulers": [
            "House Rowan"
        ],
        "founder": [],
        "_id": "5c9817ab4d1c4e54abc7ede4",
        "name": "Goldengrove",
        "location": "The Reach",
        "type": "Castle",
        "__v": 0
    },
    {
        "religion": [
            "Faith of the Seven"
        ],
        "rulers": [],
        "founder": [],
        "_id": "5c9817ab4d1c4e54abc7ede5",
        "name": "Grassy Vale",
        "location": "The Reach",
        "type": "Castle",
        "__v": 0
    },
    {
        "religion": [
            "Old Gods of the Forest",
            "Faith of the Seven"
        ],
        "rulers": [
            "Night&apos;s Watch"
        ],
        "founder": [],
        "_id": "5c9817ab4d1c4e54abc7ede6",
        "name": "Greyguard",
        "location": "The Wall",
        "type": "Castle ",
        "__v": 0
    },
    {
        "religion": [
            "Old Gods of the Forest"
        ],
        "rulers": [
            "House Reed"
        ],
        "founder": [],
        "_id": "5c9817ab4d1c4e54abc7ede7",
        "name": "Greywater Watch",
        "location": "The Neck",
        "type": "Castle",
        "__v": 0
    },
    {
        "religion": [
            "Faith of the Seven"
        ],
        "rulers": [
            "House Connington"
        ],
        "founder": [],
        "_id": "5c9817ab4d1c4e54abc7ede8",
        "name": "Griffin's Roost",
        "location": "The Stormlands",
        "type": "Castle",
        "__v": 0
    },
    {
        "religion": [
            "Drowned God"
        ],
        "rulers": [
            "House Goodbrother"
        ],
        "founder": [],
        "_id": "5c9817ab4d1c4e54abc7ede9",
        "name": "Hammerhorn",
        "location": "Great Wyk",
        "type": "Castle",
        "__v": 0
    },
    {
        "religion": [
            "Faith of the Seven",
            "Drowned God"
        ],
        "rulers": [
            "House Baelish",
            "House Bolton",
            "House Lannister",
            "House Stark",
            "House Slynt",
            "House Whent",
            "House Lothston",
            "House Strong",
            "House Harroway",
            "House Towers",
            "House Qoherys",
            "House Hoare"
        ],
        "founder": [
            "Harren Hoare"
        ],
        "_id": "5c9817ab4d1c4e54abc7edea",
        "name": "Harrenhal",
        "location": "The Riverlands",
        "type": "Castle",
        "age": 300,
        "__v": 0
    },
    {
        "religion": [
            "Faith of the Seven"
        ],
        "rulers": [
            "House Errol"
        ],
        "founder": [],
        "_id": "5c9817ab4d1c4e54abc7edeb",
        "name": "Haystack Hall",
        "location": "The Stormlands",
        "type": "Castle",
        "__v": 0
    },
    {
        "religion": [],
        "rulers": [],
        "founder": [],
        "_id": "5c9817ab4d1c4e54abc7edec",
        "name": "Heart's Home",
        "location": "The Vale of Arryn",
        "type": "Castle",
        "__v": 0
    },
    {
        "religion": [
            "Faith of the Seven"
        ],
        "rulers": [
            "House Uller"
        ],
        "founder": [],
        "_id": "5c9817ab4d1c4e54abc7eded",
        "name": "Hellholt",
        "location": "Dorne",
        "type": "Castle",
        "__v": 0
    },
    {
        "religion": [
            "Faith of the Seven"
        ],
        "rulers": [
            "House Tyrell",
            "House Gardener"
        ],
        "founder": [
            "Garth Gardener"
        ],
        "_id": "5c9817ab4d1c4e54abc7edee",
        "name": "Highgarden",
        "location": "The Reach",
        "type": "Castle, regional capital",
        "__v": 0
    },
    {
        "religion": [
            "Faith of the Seven"
        ],
        "rulers": [
            "House Whitehill"
        ],
        "founder": [],
        "_id": "5c9817ab4d1c4e54abc7edef",
        "name": "Highpoint",
        "location": "The North",
        "type": "Castle",
        "age": 1000,
        "__v": 0
    },
    {
        "religion": [
            "Faith of the Seven"
        ],
        "rulers": [
            "House Beesbury"
        ],
        "founder": [],
        "_id": "5c9817ab4d1c4e54abc7edf0",
        "name": "Honeyholt",
        "location": "The Reach",
        "type": "Castle",
        "__v": 0
    },
    {
        "religion": [
            "Faith of the Seven"
        ],
        "rulers": [
            "House Tarly"
        ],
        "founder": [],
        "_id": "5c9817ab4d1c4e54abc7edf1",
        "name": "Horn Hill",
        "location": "The Reach",
        "type": "Castle",
        "__v": 0
    },
    {
        "religion": [
            "Faith of the Seven"
        ],
        "rulers": [],
        "founder": [],
        "_id": "5c9817ab4d1c4e54abc7edf2",
        "name": "Hornvale",
        "location": "The Westerlands",
        "type": "Castle",
        "__v": 0
    },
    {
        "religion": [
            "Old Gods of the Forest"
        ],
        "rulers": [
            "House Hornwood"
        ],
        "founder": [],
        "_id": "5c9817ab4d1c4e54abc7edf3",
        "name": "Hornwood",
        "location": "The North",
        "type": "Castle",
        "__v": 0
    },
    {
        "religion": [
            "Faith of the Seven"
        ],
        "rulers": [
            "House Waynwood"
        ],
        "founder": [],
        "_id": "5c9817ab4d1c4e54abc7edf4",
        "name": "Ironoaks",
        "location": "The Vale of Arryn",
        "type": "Castle",
        "__v": 0
    },
    {
        "religion": [
            "Old Gods of the Forest"
        ],
        "rulers": [
            "House Whitehill",
            "House Forrester"
        ],
        "founder": [
            "Cedric Forrester"
        ],
        "_id": "5c9817ab4d1c4e54abc7edf5",
        "name": "Ironrath",
        "location": "The North",
        "type": "Wooden castle",
        "age": 1500,
        "__v": 0
    },
    {
        "religion": [
            "Old Gods of the Forest"
        ],
        "rulers": [
            "House Karstark"
        ],
        "founder": [
            "Karlon Stark"
        ],
        "_id": "5c9817ab4d1c4e54abc7edf6",
        "name": "Karhold",
        "location": "The North",
        "type": "Castle",
        "__v": 0
    },
    {
        "religion": [
            "Faith of the Seven"
        ],
        "rulers": [
            "House Manwoody"
        ],
        "founder": [],
        "_id": "5c9817ab4d1c4e54abc7edf7",
        "name": "Kingsgrave",
        "location": "Dorne",
        "type": "Castle",
        "__v": 0
    },
    {
        "religion": [
            "Old Gods of the Forest"
        ],
        "rulers": [
            "House Umber"
        ],
        "founder": [],
        "_id": "5c9817ab4d1c4e54abc7edf8",
        "name": "Last Hearth",
        "location": "The North",
        "type": "Castle",
        "__v": 0
    },
    {
        "religion": [
            "Faith of the Seven"
        ],
        "rulers": [
            "House Dalt"
        ],
        "founder": [],
        "_id": "5c9817ab4d1c4e54abc7edf9",
        "name": "Lemonwood",
        "location": "Dorne",
        "type": "Castle",
        "__v": 0
    },
    {
        "religion": [
            "Old Gods of the Forest",
            "Faith of the Seven"
        ],
        "rulers": [],
        "founder": [],
        "_id": "5c9817ab4d1c4e54abc7edfa",
        "name": "Long Barrow",
        "location": "The Wall",
        "type": "Castle",
        "__v": 0
    },
    {
        "religion": [
            "Faith of the Seven"
        ],
        "rulers": [
            "House Merryweather"
        ],
        "founder": [],
        "_id": "5c9817ab4d1c4e54abc7edfb",
        "name": "Long Table",
        "location": "The Reach",
        "type": "Castle",
        "__v": 0
    },
    {
        "religion": [
            "Faith of the Seven"
        ],
        "rulers": [
            "House Hunter"
        ],
        "founder": [],
        "_id": "5c9817ab4d1c4e54abc7edfc",
        "name": "Longbow Hall",
        "location": "The Vale of Arryn",
        "type": "Castle",
        "__v": 0
    },
    {
        "religion": [
            "Faith of the Seven"
        ],
        "rulers": [],
        "founder": [],
        "_id": "5c9817ab4d1c4e54abc7edfd",
        "name": "Mistwood",
        "location": "The Stormlands",
        "type": "Castle",
        "__v": 0
    },
    {
        "religion": [],
        "rulers": [
            "House Stark",
            "House Arryn",
            "House Bolton",
            "House Greyjoy"
        ],
        "founder": [],
        "_id": "5c9817ab4d1c4e54abc7edfe",
        "name": "Moat Cailin",
        "location": "The Neck",
        "type": "Castle ",
        "age": 10000,
        "__v": 0
    },
    {
        "religion": [
            "Old Gods of the Forest",
            "Faith of the Seven"
        ],
        "rulers": [
            "Night&apos;s Watch"
        ],
        "founder": [],
        "_id": "5c9817ab4d1c4e54abc7edff",
        "name": "The Nightfort",
        "location": "The Wall",
        "type": "Castle",
        "__v": 0
    },
    {
        "religion": [
            "Faith of the Seven"
        ],
        "rulers": [
            "House Caron"
        ],
        "founder": [],
        "_id": "5c9817ab4d1c4e54abc7ee00",
        "name": "Nightsong",
        "location": "The Stormlands",
        "type": "Castle",
        "__v": 0
    },
    {
        "religion": [
            "Faith of the Seven"
        ],
        "rulers": [
            "House Oakheart"
        ],
        "founder": [],
        "_id": "5c9817ab4d1c4e54abc7ee01",
        "name": "Old Oak",
        "location": "The Reach",
        "type": "Castle",
        "__v": 0
    },
    {
        "religion": [
            "Old Gods of the Forest"
        ],
        "rulers": [],
        "founder": [],
        "_id": "5c9817ab4d1c4e54abc7ee02",
        "name": "Oldcastle",
        "location": "The North",
        "type": "Castle",
        "__v": 0
    },
    {
        "religion": [],
        "rulers": [],
        "founder": [],
        "_id": "5c9817ab4d1c4e54abc7ee03",
        "name": "Palace of Justice",
        "location": "Braavos",
        "type": "Palace",
        "__v": 0
    },
    {
        "religion": [
            "Faith of the Seven"
        ],
        "rulers": [],
        "founder": [],
        "_id": "5c9817ab4d1c4e54abc7ee04",
        "name": "Pinkmaiden",
        "location": "The Riverlands",
        "type": "Castle",
        "__v": 0
    },
    {
        "religion": [
            "Drowned God"
        ],
        "rulers": [
            "House Greyjoy"
        ],
        "founder": [],
        "_id": "5c9817ab4d1c4e54abc7ee05",
        "name": "Pyke (castle)",
        "location": "Westeros",
        "type": "Castle, regional capital",
        "__v": 0
    },
    {
        "religion": [
            "Old Gods of the Forest",
            "Faith of the Seven"
        ],
        "rulers": [],
        "founder": [],
        "_id": "5c9817ab4d1c4e54abc7ee06",
        "name": "Queensgate",
        "location": "The Wall",
        "type": "Castle",
        "__v": 0
    },
    {
        "religion": [
            "Faith of the Seven"
        ],
        "rulers": [
            "House Wylde"
        ],
        "founder": [],
        "_id": "5c9817ab4d1c4e54abc7ee07",
        "name": "Rain House",
        "location": "The Stormlands",
        "type": "Castle",
        "__v": 0
    },
    {
        "religion": [
            "Old Gods of the Forest"
        ],
        "rulers": [],
        "founder": [],
        "_id": "5c9817ab4d1c4e54abc7ee08",
        "name": "Ramsgate",
        "location": "The North",
        "type": "Castle",
        "__v": 0
    },
    {
        "religion": [
            "Old Gods of the Forest"
        ],
        "rulers": [
            "House Blackwood"
        ],
        "founder": [],
        "_id": "5c9817ab4d1c4e54abc7ee09",
        "name": "Raventree Hall",
        "location": "The Riverlands",
        "type": "Castle",
        "__v": 0
    },
    {
        "religion": [
            "Faith of the Seven"
        ],
        "rulers": [
            "King of the Andals, the Rhoynar, and the First Men",
            "House Lannister"
        ],
        "founder": [
            "Aegon I Targaryen",
            "Maegor Targaryen"
        ],
        "_id": "5c9817ab4d1c4e54abc7ee0a",
        "name": "Red Keep",
        "location": "King's Landing",
        "type": "CastleAdministrative center",
        "age": 303,
        "__v": 0
    },
    {
        "religion": [
            "Faith of the Seven"
        ],
        "rulers": [],
        "founder": [],
        "_id": "5c9817ab4d1c4e54abc7ee0b",
        "name": "Red Lake",
        "location": "The Reach",
        "type": "Castle",
        "__v": 0
    },
    {
        "religion": [
            "Faith of the Seven"
        ],
        "rulers": [],
        "founder": [],
        "_id": "5c9817ab4d1c4e54abc7ee0c",
        "name": "The Redfort",
        "location": "The Vale of Arryn",
        "type": "Castle",
        "__v": 0
    },
    {
        "religion": [],
        "rulers": [
            "House Glenmore"
        ],
        "founder": [],
        "_id": "5c9817ab4d1c4e54abc7ee0d",
        "name": "Rillwater Crossing",
        "location": "The Rills",
        "type": "Castle",
        "__v": 0
    },
    {
        "religion": [
            "Faith of the Seven"
        ],
        "rulers": [
            "House Frey",
            "House Tully"
        ],
        "founder": [],
        "_id": "5c9817ab4d1c4e54abc7ee0e",
        "name": "Riverrun",
        "location": "The Riverlands",
        "type": "Castle, regional capital",
        "age": 1000,
        "__v": 0
    },
    {
        "religion": [
            "Faith of the Seven"
        ],
        "rulers": [
            "House Rosby"
        ],
        "founder": [],
        "_id": "5c9817ab4d1c4e54abc7ee0f",
        "name": "Rosby",
        "location": "The Crownlands",
        "type": "Castle and town",
        "__v": 0
    },
    {
        "religion": [
            "Faith of the Seven"
        ],
        "rulers": [
            "House Royce"
        ],
        "founder": [],
        "_id": "5c9817ab4d1c4e54abc7ee10",
        "name": "Runestone",
        "location": "The Vale of Arryn",
        "type": "Castle",
        "__v": 0
    },
    {
        "religion": [
            "Faith of the Seven"
        ],
        "rulers": [],
        "founder": [],
        "_id": "5c9817ab4d1c4e54abc7ee11",
        "name": "Saltshore",
        "location": "Dorne",
        "type": "Castle",
        "__v": 0
    },
    {
        "religion": [
            "Faith of the Seven"
        ],
        "rulers": [
            "House Qorgyle"
        ],
        "founder": [],
        "_id": "5c9817ab4d1c4e54abc7ee12",
        "name": "Sandstone",
        "location": "Dorne",
        "type": "Castle",
        "__v": 0
    },
    {
        "religion": [
            "Faith of the Seven"
        ],
        "rulers": [
            "House Sarsfield"
        ],
        "founder": [],
        "_id": "5c9817ab4d1c4e54abc7ee13",
        "name": "Sarsfield",
        "location": "The Westerlands",
        "type": "Castle",
        "__v": 0
    },
    {
        "religion": [
            "Faith of the Seven"
        ],
        "rulers": [
            "House Mallister"
        ],
        "founder": [],
        "_id": "5c9817ab4d1c4e54abc7ee14",
        "name": "Seagard",
        "location": "The Riverlands",
        "type": "CastleTown",
        "__v": 0
    },
    {
        "religion": [],
        "rulers": [
            "Sealord of Braavos"
        ],
        "founder": [],
        "_id": "5c9817ab4d1c4e54abc7ee15",
        "name": "Sealord's Palace",
        "location": "Braavos",
        "type": "Palace",
        "__v": 0
    },
    {
        "religion": [
            "Old Gods of the Forest",
            "Faith of the Seven"
        ],
        "rulers": [
            "Night&apos;s Watch"
        ],
        "founder": [],
        "_id": "5c9817ab4d1c4e54abc7ee16",
        "name": "The Shadow Tower",
        "location": "The Wall",
        "type": "Castle",
        "__v": 0
    },
    {
        "religion": [
            "Faith of the Seven"
        ],
        "rulers": [],
        "founder": [],
        "_id": "5c9817ab4d1c4e54abc7ee17",
        "name": "Sharp Point",
        "location": "The Crownlands",
        "type": "Castle",
        "__v": 0
    },
    {
        "religion": [
            "Faith of the Seven"
        ],
        "rulers": [
            "House Serrett"
        ],
        "founder": [],
        "_id": "5c9817ab4d1c4e54abc7ee18",
        "name": "Silverhill",
        "location": "The Westerlands",
        "type": "Castle",
        "__v": 0
    },
    {
        "religion": [
            "Faith of the Seven"
        ],
        "rulers": [],
        "founder": [],
        "_id": "5c9817ab4d1c4e54abc7ee19",
        "name": "Skyreach",
        "location": "Dorne",
        "type": "Castle",
        "__v": 0
    },
    {
        "religion": [
            "Faith of the Seven"
        ],
        "rulers": [
            "House Dayne"
        ],
        "founder": [],
        "_id": "5c9817ab4d1c4e54abc7ee1a",
        "name": "Starfall",
        "location": "Dorne",
        "type": "Castle",
        "__v": 0
    },
    {
        "religion": [
            "Faith of the Seven"
        ],
        "rulers": [
            "House Bracken"
        ],
        "founder": [],
        "_id": "5c9817ab4d1c4e54abc7ee1b",
        "name": "Stone Hedge",
        "location": "The Riverlands",
        "type": "Castle",
        "__v": 0
    },
    {
        "religion": [
            "Faith of the Seven"
        ],
        "rulers": [],
        "founder": [],
        "_id": "5c9817ab4d1c4e54abc7ee1c",
        "name": "Stonedance",
        "location": "The Crownlands",
        "type": "Castle",
        "__v": 0
    },
    {
        "religion": [
            "Faith of the Seven"
        ],
        "rulers": [
            "House Swann"
        ],
        "founder": [],
        "_id": "5c9817ab4d1c4e54abc7ee1d",
        "name": "Stonehelm",
        "location": "Westeros",
        "type": "Castle",
        "__v": 0
    },
    {
        "religion": [
            "Faith of the Seven"
        ],
        "rulers": [
            "House Baratheon of King&apos;s Landing",
            "House Baratheon of Storm&apos;s End",
            "House Baratheon of Dragonstone",
            "House Durrandon"
        ],
        "founder": [
            "Durran",
            "Brandon Stark (the Builder)"
        ],
        "_id": "5c9817ab4d1c4e54abc7ee1e",
        "name": "Storm's End",
        "location": "The Stormlands",
        "type": "CastleRegional capital",
        "__v": 0
    },
    {
        "religion": [],
        "rulers": [
            "House Targaryen"
        ],
        "founder": [
            "King of the Andals, the Rhoynar, and the First Men",
            "Daeron II Targaryen"
        ],
        "_id": "5c9817ab4d1c4e54abc7ee1f",
        "name": "Summerhall",
        "location": "The Stormlands",
        "type": "Castle",
        "__v": 0
    },
    {
        "religion": [
            "Faith of the Seven"
        ],
        "rulers": [
            "House Cuy"
        ],
        "founder": [],
        "_id": "5c9817ab4d1c4e54abc7ee20",
        "name": "Sunflower Hall",
        "location": "The Reach",
        "type": "Castle",
        "__v": 0
    },
    {
        "religion": [
            "Faith of the Seven"
        ],
        "rulers": [
            "Ellaria Sand",
            "House Martell"
        ],
        "founder": [],
        "_id": "5c9817ab4d1c4e54abc7ee21",
        "name": "Sunspear",
        "location": "Dorne",
        "type": "Castle, regional capital",
        "age": 1000,
        "__v": 0
    },
    {
        "religion": [
            "Faith of the Seven"
        ],
        "rulers": [
            "House Tarbeck"
        ],
        "founder": [],
        "_id": "5c9817ab4d1c4e54abc7ee22",
        "name": "Tarbeck Hall",
        "location": "The Westerlands",
        "type": "Castle",
        "__v": 0
    },
    {
        "religion": [
            "Drowned God"
        ],
        "rulers": [
            "House Harlaw"
        ],
        "founder": [],
        "_id": "5c9817ab4d1c4e54abc7ee23",
        "name": "Ten Towers",
        "location": "Harlaw",
        "type": "Castle",
        "__v": 0
    },
    {
        "religion": [
            "Faith of the Seven"
        ],
        "rulers": [],
        "founder": [],
        "_id": "5c9817ab4d1c4e54abc7ee24",
        "name": "Three Towers",
        "location": "The Reach",
        "type": "Castle",
        "__v": 0
    },
    {
        "religion": [
            "Faith of the Seven"
        ],
        "rulers": [
            "House Jordayne"
        ],
        "founder": [],
        "_id": "5c9817ab4d1c4e54abc7ee25",
        "name": "The Tor",
        "location": "Dorne",
        "type": "Castle",
        "__v": 0
    },
    {
        "religion": [
            "Old Gods of the Forest",
            "Drowned God"
        ],
        "rulers": [
            "House Tallhart"
        ],
        "founder": [],
        "_id": "5c9817ab4d1c4e54abc7ee26",
        "name": "Torrhen's Square",
        "location": "The North",
        "type": "Castle",
        "__v": 0
    },
    {
        "religion": [
            "Faith of the Seven"
        ],
        "rulers": [],
        "founder": [],
        "_id": "5c9817ab4d1c4e54abc7ee27",
        "name": "Tumbleton",
        "location": "The Reach",
        "type": "Castle",
        "__v": 0
    },
    {
        "religion": [
            "Faith of the Seven"
        ],
        "rulers": [
            "House Frey"
        ],
        "founder": [],
        "_id": "5c9817ab4d1c4e54abc7ee28",
        "name": "The Twins",
        "location": "The Riverlands",
        "type": "Two bridged castles",
        "age": 600,
        "__v": 0
    },
    {
        "religion": [],
        "rulers": [
            "House Baelish"
        ],
        "founder": [
            "Baelish (founder)"
        ],
        "_id": "5c9817ab4d1c4e54abc7ee29",
        "name": "Unnamed Baelish castle",
        "location": "The Fingers",
        "type": "Castle",
        "__v": 0
    },
    {
        "religion": [
            "Faith of the Seven"
        ],
        "rulers": [],
        "founder": [],
        "_id": "5c9817ab4d1c4e54abc7ee2a",
        "name": "Uplands",
        "location": "The Reach",
        "type": "Castle",
        "__v": 0
    },
    {
        "religion": [
            "Faith of the Seven"
        ],
        "rulers": [],
        "founder": [],
        "_id": "5c9817ab4d1c4e54abc7ee2b",
        "name": "Vaith",
        "location": "Dorne",
        "type": "Castle",
        "__v": 0
    },
    {
        "religion": [],
        "rulers": [],
        "founder": [],
        "_id": "5c9817ab4d1c4e54abc7ee2c",
        "name": "Vulture's Roost",
        "location": "Dorne",
        "type": "Castle",
        "__v": 0
    },
    {
        "religion": [],
        "rulers": [],
        "founder": [],
        "_id": "5c9817ab4d1c4e54abc7ee2d",
        "name": "The Whispers",
        "location": "The Crownlands",
        "type": "Castle",
        "__v": 0
    },
    {
        "religion": [
            "Faith of the Seven"
        ],
        "rulers": [],
        "founder": [],
        "_id": "5c9817ab4d1c4e54abc7ee2e",
        "name": "Whitewalls",
        "location": "The Riverlands",
        "type": "Castle",
        "__v": 0
    },
    {
        "religion": [
            "Old Gods of the Forest"
        ],
        "rulers": [],
        "founder": [],
        "_id": "5c9817ab4d1c4e54abc7ee2f",
        "name": "Widow's Watch",
        "location": "The North",
        "type": "Castle",
        "__v": 0
    },
    {
        "religion": [
            "Old Gods of the Forest"
        ],
        "rulers": [
            "House Stark",
            "House Bolton",
            "House Greyjoy"
        ],
        "founder": [
            "Brandon Stark (the Builder)"
        ],
        "_id": "5c9817ab4d1c4e54abc7ee30",
        "name": "Winterfell",
        "location": "The North",
        "type": "CastleRegional capital",
        "age": 8000,
        "__v": 0
    },
    {
        "religion": [
            "Faith of the Seven"
        ],
        "rulers": [],
        "founder": [],
        "_id": "5c9817ab4d1c4e54abc7ee31",
        "name": "Wyl (castle)",
        "location": "Dorne",
        "type": "Castle",
        "__v": 0
    },
    {
        "religion": [
            "Faith of the Seven"
        ],
        "rulers": [
            "House Yronwood"
        ],
        "founder": [],
        "_id": "5c9817ab4d1c4e54abc7ee32",
        "name": "Yronwood",
        "location": "Dorne",
        "type": "Castle",
        "__v": 0
    }
]
